{ "meaning_Shvedova": "причинно-следственное", "conjunction": "а как", "constr_type": "причинная", "formula": "а как clause, то и clause", "id_doc": "15", "formula_new": "а как clause, то и clause", "page_book": "119", "text_first_using": "Но понеже собранїемъ сената и подлежащими голосами, предложенїе его, безъ всякаго противор?чїя и спору разсуждено обществу полезнымъ, то посл? онъ, съ возложенїемъ на него изъ цв?товъ сплетеннаго в?нца, для торжества, съ посл?дованїемъ и восклицанїемъ народа, водимъ былъ по всему городу, а какъ по прошествїи времяни, еще больше усмотрено, сколь великую пользу, уничтоженїе помянутаго обычая, въ народ? ихъ причинило, то и Кадокїемъ или великимъ канцлеромъ его зд?лали. [Стефан Савицкий (перевод книги Л. Хольберга). Подземное путешествїе представляющее Исторїю разнородныхъ съ удивительными и неслыханными свойствами животныхъ (1762)]", "page_pdf": "59", "special_word": "то и", "comments": "", "other_examples": "", "text_last_using": "А ведь есть еще чиновные шинельные бобры (положенные офицерству и чиновникам высших четырех классов) ? и если сначала шел Акакий Акакиевич по улицам с тощим освещением, то ничего величественного и не видел, «а как улицы становились сильнее освещены, то и пешеходы стали мелькать чаще, начали попадаться дамы, красиво одетые, на мужчинах попадались бобровые воротники». [Евгения Пищикова. Пятиэтажная Россия (2007) // «Русская Жизнь», 2008]", "year_first_using": "1762", "meaning": "причинно-следственное", "year_last_using": "2008"}