{ "meaning_Shvedova": "одновременность ", "conjunction": "когда", "constr_type": "временная", "formula": "когда VP, то VP", "id_doc": "153", "formula_new": "0", "page_book": "148", "text_first_using": "А когда дошел до вышеписанной мызы, то оную обрел укрепленую около каменного дому земляною крепостью и полисадами, которую осадя, оной полковник послал к фелтьмаршалу с известием, что ее с одним полком достать не может. [А. М. Макаров (ред.). Гистория Свейской войны (Поденная записка Петра Великого) (1698-1721)] ", "page_pdf": "74", "special_word": "то", "comments": "0", "other_examples": "Когда мне представлялось, что я солдат, то какой-то луч надежды сверкал передо мною. [Н. Ф. Павлов. Именины (1835)]", "text_last_using": "Более того, мы недавно увидели, что когда кто-то в этом районе продает квартиру, то обязательно в списке преимуществ района указывает, что рядом ? православный храм. [А. А. Данилова. Местность любви (2015.11.09)] ", "year_first_using": "1698", "meaning": "одновременность ", "year_last_using": "2015"}