{ "meaning_Shvedova": "одновременность ", "conjunction": "как", "constr_type": "временная", "formula": "тогда VP, как VP", "id_doc": "157", "formula_new": "тогда VP, когда VP", "page_book": "149", "text_first_using": "то есть, трубку, в A залитую и другим концом B опущенную во ртуть, в сосудец CD влитую, под колоколом ABCD поставь и воздух из трубки AB, как прежде (§56) из шара, вытяни, тогда ртуть в трубку подымется, как только внешний воздух впущен будет. [М. В. Ломоносов. Волфианская экспериментальная физика, с немецкого подлинника на латинском языке сокращенная (1745)] ", "page_pdf": "74", "special_word": "тогда", "comments": "0", "other_examples": "Дед мой находился тогда в службе, как она умерла. [А. Т. Болотов. Жизнь и приключения Андрея Болотова (1759)]", "text_last_using": "Я с восхищением тогда слушаю, как моя писклявая скрипка вдруг начинает петь глубокими звуками. [Самуил Алешин. Встречи на грешной земле (2001)]", "year_first_using": "1745", "meaning": "одновременность ", "year_last_using": "2001"}