{ "meaning_Shvedova": "уступка", "conjunction": "куда ни", "constr_type": "уступительно-обобщительная", "formula": "куда ни VP, clause", "id_doc": "70", "formula_new": "куда ни VP, clause", "page_book": "112", "text_first_using": "Куда ни обращу взор мой, везде вижу власть красноречия. [В. К. Тредиаковский, И. Войцехович. Сокращение речи г. Тредьяковского о богатом, различном, искусном и несходственном витийстве]", "page_pdf": "56", "special_word": "0", "comments": "", "other_examples": "", "text_last_using": "?] 72 еще куда ни шло, но тоже хорошего мало. [коллективный. Рейтинг нижегородских автобусных перевозчиков. Поставь свою оценку! [опрос]]", "year_first_using": "1748", "meaning": "уступка", "year_last_using": "2015"}